em_transfer_learning/lgmm.py
em_transfer_learning/transfer_learning.py
em_transfer_learning-1.0.0.dist-info/LICENSE
em_transfer_learning-1.0.0.dist-info/METADATA
em_transfer_learning-1.0.0.dist-info/WHEEL
em_transfer_learning-1.0.0.dist-info/top_level.txt
em_transfer_learning-1.0.0.dist-info/RECORD
