Metadata-Version: 2.1
Name: em-transfer-learning
Version: 1.0.0
Summary: Supervised linear transfer learning based on labelled Gaussian mixture models and expectation maximization in scikit-learn-compatible form.
Home-page: https://gitlab.ub.uni-bielefeld.de/bpaassen/transfer-learning
Author: Benjamin Paassen
Author-email: bpaassen@techfak.uni-bielefeld.de
License: UNKNOWN
Keywords: transfer-learning gaussian-mixture-models learning-vector-quantization gmm lvq
Platform: UNKNOWN
Classifier: Programming Language :: Python :: 3
Classifier: License :: OSI Approved :: GNU General Public License v3 (GPLv3)
Classifier: Operating System :: OS Independent
Requires-Dist: numpy
Requires-Dist: scikit-learn
Requires-Dist: scipy
